cloudfn/aws/deploy.py
cloudfn/aws/event.py
cloudfn/aws/layer_builder.py
cloudfn/aws/local.py
cloudfn/aws/model.py
cloudfn/aws/util.py
cloudfn_aws-0.2.12.dist-info/METADATA
cloudfn_aws-0.2.12.dist-info/WHEEL
cloudfn_aws-0.2.12.dist-info/top_level.txt
cloudfn_aws-0.2.12.dist-info/RECORD
